{
  "overview": "A URL shortener service with two backend APIs: the original shortener API that generates unique short codes and handles redirection, and a new analytics service that records redirect events. The shortener API communicates asynchronously with the analytics service via HTTP POST on each redirect to log source IP, user-agent, and timestamp. The analytics service exposes a GET endpoint to retrieve statistics per short code.",
  "requirements": [
    "The API must accept a long URL via POST request and return a unique short code",
    "The API must redirect users from short code to original long URL via GET request",
    "Short codes must be unique across all stored URLs",
    "The same long URL can be shortened multiple times, generating different short codes each time",
    "Short codes must use alphanumeric characters (letters and numbers) only",
    "Short codes must be compact in length",
    "The system must handle collision detection to ensure uniqueness",
    "The API must expose a /health endpoint for readiness checks",
    "The redirect must use appropriate HTTP status code (301 or 302)",
    "Every redirect event must be recorded with source IP, user-agent, and timestamp",
    "The analytics service must expose GET /stats/{code} endpoint to retrieve redirect statistics",
    "The analytics service must store redirect events persistently in-memory",
    "The shortener API must send redirect events to the analytics service asynchronously"
  ],
  "components": [
    {
      "name": "url-shortener-api",
      "componentType": "service",
      "language": "Go",
      "dependsOn": [],
      "entrypoint": "deployment/service",
      "buildpack": "docker",
      "appPath": "/url-shortener-api",
      "openAPISpec": "openapi: 3.0.3\ninfo:\n  title: URL Shortener API\n  version: 1.0.0\n  description: API for creating short URLs and redirecting to original URLs\nservers:\n  - url: http://localhost:9090\npaths:\n  /health:\n    get:\n      summary: Health check endpoint\n      operationId: healthCheck\n      responses:\n        '200':\n          description: Service is healthy\n          content:\n            application/json:\n              schema:\n                type: object\n                properties:\n                  status:\n                    type: string\n                    example: ok\n  /shorten:\n    post:\n      summary: Create a short URL\n      operationId: shortenURL\n      requestBody:\n        required: true\n        content:\n          application/json:\n            schema:\n              type: object\n              required:\n                - url\n              properties:\n                url:\n                  type: string\n                  format: uri\n                  description: The long URL to shorten\n                  example: https://example.com/very/long/path/to/resource\n      responses:\n        '201':\n          description: Short URL created successfully\n          content:\n            application/json:\n              schema:\n                type: object\n                properties:\n                  shortCode:\n                    type: string\n                    description: The generated short code\n                    example: abc123\n                  shortUrl:\n                    type: string\n                    format: uri\n                    description: The complete short URL\n                    example: http://localhost:9090/abc123\n                  originalUrl:\n                    type: string\n                    format: uri\n                    description: The original long URL\n                    example: https://example.com/very/long/path/to/resource\n        '400':\n          description: Invalid request\n          content:\n            application/json:\n              schema:\n                type: object\n                properties:\n                  error:\n                    type: string\n                    example: url field is required\n        '500':\n          description: Server error\n          content:\n            application/json:\n              schema:\n                type: object\n                properties:\n                  error:\n                    type: string\n                    example: failed to generate short code\n  /{shortCode}:\n    get:\n      summary: Redirect to original URL\n      operationId: redirectToOriginal\n      parameters:\n        - name: shortCode\n          in: path\n          required: true\n          schema:\n            type: string\n          description: The short code to redirect\n          example: abc123\n      responses:\n        '302':\n          description: Redirect to original URL\n          headers:\n            Location:\n              schema:\n                type: string\n                format: uri\n              description: The original long URL\n        '404':\n          description: Short code not found\n          content:\n            application/json:\n              schema:\n                type: object\n                properties:\n                  error:\n                    type: string\n                    example: short code not found",
      "componentAgentInstructions": "Implement a URL shortener service in Go using net/http on port 9090. Create three endpoints: GET /health returns {\"status\":\"ok\"} with 200 status. POST /shorten accepts JSON body with 'url' field containing the long URL to shorten. Generate a unique short code using alphanumeric characters (a-z, A-Z, 0-9) with length 6-8 characters. Use a random generation approach and check for collisions against existing codes in storage. Store the mapping from short code to original URL in an in-memory map protected by a mutex for thread safety. Return 201 with JSON containing shortCode, shortUrl (full URL with short code), and originalUrl. Return 400 if url field is missing or invalid. Return 500 if code generation fails after reasonable retries. GET /{shortCode} looks up the short code in storage and returns 302 redirect with Location header set to the original URL. Return 404 with JSON error if short code doesn't exist. The same long URL shortened multiple times must generate different short codes each time (no deduplication). Use crypto/rand for generating random codes to ensure uniqueness. Implement proper error handling, request validation, and logging. Use standard library encoding/json for JSON handling. The service should be stateless except for the in-memory URL store. Include Dockerfile with multi-stage build using golang:1.21-alpine for build and alpine:latest for runtime. Expose port 9090. No external dependencies or databases required."
    },
    {
      "name": "analytics-service",
      "componentType": "service",
      "language": "Go",
      "dependsOn": [],
      "entrypoint": "deployment/service",
      "buildpack": "docker",
      "appPath": "/analytics-service",
      "openAPISpec": "openapi: 3.0.3\ninfo:\n  title: Analytics Service API\n  version: 1.0.0\n  description: Service for recording and retrieving URL redirect analytics\nservers:\n  - url: http://localhost:9090\npaths:\n  /health:\n    get:\n      summary: Health check endpoint\n      operationId: healthCheck\n      responses:\n        '200':\n          description: Service is healthy\n          content:\n            application/json:\n              schema:\n                type: object\n                properties:\n                  status:\n                    type: string\n                    example: ok\n  /events:\n    post:\n      summary: Record a redirect event\n      operationId: recordEvent\n      requestBody:\n        required: true\n        content:\n          application/json:\n            schema:\n              type: object\n              required:\n                - shortCode\n                - sourceIp\n                - userAgent\n                - timestamp\n              properties:\n                shortCode:\n                  type: string\n                  description: The short code that was accessed\n                  example: abc123\n                sourceIp:\n                  type: string\n                  description: IP address of the requester\n                  example: 192.168.1.1\n                userAgent:\n                  type: string\n                  description: User-Agent header from the request\n                  example: Mozilla/5.0\n                timestamp:\n                  type: string\n                  format: date-time\n                  description: ISO 8601 timestamp of the event\n                  example: 2023-10-15T14:30:00Z\n      responses:\n        '201':\n          description: Event recorded successfully\n          content:\n            application/json:\n              schema:\n                type: object\n                properties:\n                  status:\n                    type: string\n                    example: recorded\n        '400':\n          description: Invalid request\n          content:\n            application/json:\n              schema:\n                type: object\n                properties:\n                  error:\n                    type: string\n                    example: missing required fields\n        '500':\n          description: Server error\n          content:\n            application/json:\n              schema:\n                type: object\n                properties:\n                  error:\n                    type: string\n                    example: failed to record event\n  /stats/{code}:\n    get:\n      summary: Retrieve statistics for a short code\n      operationId: getStats\n      parameters:\n        - name: code\n          in: path\n          required: true\n          schema:\n            type: string\n          description: The short code to retrieve stats for\n          example: abc123\n      responses:\n        '200':\n          description: Statistics retrieved successfully\n          content:\n            application/json:\n              schema:\n                type: object\n                properties:\n                  shortCode:\n                    type: string\n                    example: abc123\n                  totalClicks:\n                    type: integer\n                    example: 42\n                  events:\n                    type: array\n                    items:\n                      type: object\n                      properties:\n                        sourceIp:\n                          type: string\n                          example: 192.168.1.1\n                        userAgent:\n                          type: string\n                          example: Mozilla/5.0\n                        timestamp:\n                          type: string\n                          format: date-time\n                          example: 2023-10-15T14:30:00Z\n        '404':\n          description: No statistics found for the short code\n          content:\n            application/json:\n              schema:\n                type: object\n                properties:\n                  error:\n                    type: string\n                    example: no stats found for code\n        '500':\n          description: Server error\n          content:\n            application/json:\n              schema:\n                type: object\n                properties:\n                  error:\n                    type: string\n                    example: failed to retrieve stats",
      "componentAgentInstructions": "Implement an analytics service in Go using net/http on port 9090. Create three endpoints: GET /health returns {\"status\":\"ok\"} with 200 status. POST /events accepts JSON body with required fields: shortCode (string), sourceIp (string), userAgent (string), and timestamp (ISO 8601 date-time string). Store each event in an in-memory data structure organized by shortCode. Use a map from shortCode to a slice of event objects, protected by a mutex for thread safety. Each event object contains sourceIp, userAgent, and timestamp. Return 201 with {\"status\":\"recorded\"} on success. Return 400 if any required field is missing or timestamp is invalid. Return 500 on internal errors. GET /stats/{code} retrieves all recorded events for the given short code. Return 200 with JSON object containing shortCode, totalClicks (count of events), and events array (all recorded events with sourceIp, userAgent, timestamp). Return 404 with JSON error if no events exist for the code. Return 500 on internal errors. Use standard library encoding/json for JSON handling. Parse and validate ISO 8601 timestamps using time.RFC3339. Implement proper error handling, request validation, and logging. The service should be stateless except for the in-memory event store. Include Dockerfile with multi-stage build using golang:1.21-alpine for build and alpine:latest for runtime. Expose port 9090. No external dependencies or databases required."
    }
  ],
  "sourceSpec": "spec-v2"
}